pystmcube/__init__.py
pystmcube/api.py
pystmcube-0.0.2.dist-info/METADATA
pystmcube-0.0.2.dist-info/WHEEL
pystmcube-0.0.2.dist-info/RECORD
